majortom_gateway/__init__.py
majortom_gateway/command.py
majortom_gateway/gateway_api.py
majortom_gateway-0.1.4.dist-info/LICENSE
majortom_gateway-0.1.4.dist-info/METADATA
majortom_gateway-0.1.4.dist-info/WHEEL
majortom_gateway-0.1.4.dist-info/top_level.txt
majortom_gateway-0.1.4.dist-info/RECORD
