Metadata-Version: 2.1
Name: majortom-gateway
Version: 0.1.4
Summary: A package for interacting with Major Tom's Gateway API.
Home-page: https://github.com/kubos/majortom_gateway_package
Author: Kubos
Author-email: open-source@kubos.com
Keywords: majortom major_tom gateway kubos major tom satellite
Classifier: Programming Language :: Python :: 3
Classifier: Programming Language :: Python :: 3.6
Classifier: Programming Language :: Python :: 3 :: Only
Classifier: Topic :: Software Development :: Libraries :: Python Modules
Classifier: Intended Audience :: Developers
Classifier: License :: OSI Approved :: Apache Software License
Classifier: Operating System :: OS Independent
Requires-Python: >=3.6
License-File: LICENSE
Requires-Dist: websockets
Requires-Dist: requests
Requires-Dist: asgiref
